magic_toolbox/.pytest_cache/.gitignore
magic_toolbox/.pytest_cache/CACHEDIR.TAG
magic_toolbox/.pytest_cache/README.md
magic_toolbox/.pytest_cache/v/cache/lastfailed
magic_toolbox/.pytest_cache/v/cache/nodeids
magic_toolbox/.pytest_cache/v/cache/stepwise
magic_toolbox/foo/foo.py
magic_toolbox/foo/tools.py
magic_toolbox/magic_toolbox.py
magic_toolbox/test_magic_toolbox.py
magic_toolbox-0.1.11.dist-info/LICENSE
magic_toolbox-0.1.11.dist-info/METADATA
magic_toolbox-0.1.11.dist-info/WHEEL
magic_toolbox-0.1.11.dist-info/entry_points.txt
magic_toolbox-0.1.11.dist-info/RECORD
