Metadata-Version: 2.1
Name: magic-toolbox
Version: 0.1.11
Summary: A cli framwork in same vane as django
License: Apache2.0
Author: daniel davee
Author-email: daniel.v.davee@gmail.com
Requires-Python: >=3.10,<4.0
Classifier: License :: Other/Proprietary License
Classifier: Programming Language :: Python :: 3
Classifier: Programming Language :: Python :: 3.10
Classifier: Programming Language :: Python :: 3.11
Requires-Dist: inquirerpy (>=0.3.4,<0.4.0)
Requires-Dist: plac (>=1.4.2,<2.0.0)
